week7/tgc2.v
module tgc2 (a,b,c,Q);
    input [7:0] a,b,c;
    output Q;
    reg cnt;
    
    always @(a,b,c) begin
        cnt=1'b0;
        if (({1'b0,a}+{1'b0,b})>c && ({1'b0,a}+{1'b0,c})>b && ({1'b0,b}+{1'b0,c})>a) begin
            cnt=1'b1;
        end
    end   

    assign Q=cnt; 
endmodule

week7/tgc2_tb.v
`timescale 1 ps / 1 ps
module tgc2_tb;
reg [7:0] a,b,c;
wire  Q;
parameter STEP = 1000;
tgc2 tgc_test(.a(a),.b(b),.c(c),.Q(Q));
initial begin
    $dumpfile("tgc2_tb.vcd");
    $dumpvars(0, tgc2_tb);
    $monitor( $stime, " a=%b b=%b c=%b Q=%b", a,b,c,Q);
    #STEP a = 8'b00000011; b = 8'b00000100; c = 8'b00001010; 
    #STEP a = 8'b00000011; b = 8'b00000100; c = 8'b00000101; 
    #STEP a = 8'b10010101; b = 8'b00101010; c = 8'b10010101; 
    #STEP a = 8'b01101011; b = 8'b10111011; c = 8'b01111010; 
    #STEP a = 8'b00011011; b = 8'b11010100; c = 8'b11010101; 
    #STEP a = 8'b11101101; b = 8'b11011101; c = 8'b11110011; 
    #STEP a = 8'b11111010; b = 8'b11111101; c = 8'b11010110; 
    #STEP a = 8'b11000011; b = 8'b00000111; c = 8'b11110101; 
    #STEP a = 8'b00110010; b = 8'b11111001; c = 8'b11101110; 
    #STEP a = 8'b11111000; b = 8'b11011001; c = 8'b10001110; 
    #STEP $finish;
end
endmodule

week7/tgc2_tb.vcd
$date
	Mon Sep 20 13:00:12 2021
$end
$version
	Icarus Verilog
$end
$timescale
	1ps
$end
$scope module tgc2_tb $end
$var wire 1 ! Q $end
$var reg 8 " a [7:0] $end
$var reg 8 # b [7:0] $end
$var reg 8 $ c [7:0] $end
$scope module tgc_test $end
$var wire 1 ! Q $end
$var wire 8 % a [7:0] $end
$var wire 8 & b [7:0] $end
$var wire 8 ' c [7:0] $end
$var reg 1 ( cnt $end
$upscope $end
$upscope $end
$enddefinitions $end
#0
$dumpvars
x(
bx '
bx &
bx %
bx $
bx #
bx "
x!
$end
#1000
0(
0!
b1010 $
b1010 '
b100 #
b100 &
b11 "
b11 %
#2000
1(
1!
b101 $
b101 '
#3000
1(
1!
b10010101 $
b10010101 '
b101010 #
b101010 &
b10010101 "
b10010101 %
#4000
1(
1!
b1111010 $
b1111010 '
b10111011 #
b10111011 &
b1101011 "
b1101011 %
#5000
1(
1!
b11010101 $
b11010101 '
b11010100 #
b11010100 &
b11011 "
b11011 %
#6000
1(
1!
b11110011 $
b11110011 '
b11011101 #
b11011101 &
b11101101 "
b11101101 %
#7000
1(
1!
b11010110 $
b11010110 '
b11111101 #
b11111101 &
b11111010 "
b11111010 %
#8000
0(
0!
b11110101 $
b11110101 '
b111 #
b111 &
b11000011 "
b11000011 %
#9000
1(
1!
b11101110 $
b11101110 '
b11111001 #
b11111001 &
b110010 "
b110010 %
#10000
1(
1!
b10001110 $
b10001110 '
b11011001 #
b11011001 &
b11111000 "
b11111000 %
