week6/population_counter.v
module population_counter ( a, Q );
    input  [31:0] a;
    output  [5:0] Q;
    reg [5:0] cnt;
    integer i;

    always @( a ) begin
        cnt = 6'b0;
        for ( i=0 ; i<32 ; i=i+1 ) begin
            if (a[i] == 1'b1) begin
                cnt = cnt + 6'b1;
            end
        end
    end
    assign Q = cnt;
endmodule

week6/population_counter_tb.v
`timescale 1 ps / 1 ps
module population_counter_tb;
reg [31:0] a;
wire [5:0] Q;
parameter STEP = 1000;
population_counter population_counter_test(.a(a), .Q(Q));
initial begin
    $dumpfile("population_counter_tb.vcd");
    $dumpvars(0, population_counter_tb);
    $monitor( $stime, " a=%b Q=%b", a, Q);
    #STEP a = 32'b11111111111111111111111111111111;
    #STEP a = 32'b11010001100010101011011000100110;
    #STEP a = 32'b10110001100011111000011010101010;
    #STEP a = 32'b11001010000111001010001001110001;
    #STEP a = 32'b10100110001111000101010101111100;   
    #STEP a = 32'b10101011101010001001010101010111;
    #STEP a = 32'b11010101111010101001011011101110;
    #STEP a = 32'b10111101001100111110111110101000;
    #STEP a = 32'b11111011110110001010001001110101;
    #STEP a = 32'b10110011101011101011101001110101; 
    #STEP $finish;
end
endmodule

week6/population_counter_tb.vcd
$date
	Mon Sep 06 15:03:07 2021
$end
$version
	Icarus Verilog
$end
$timescale
	1ps
$end
$scope module population_counter_tb $end
$var wire 6 ! Q [5:0] $end
$var reg 32 " a [31:0] $end
$scope module population_counter_test $end
$var wire 6 # Q [5:0] $end
$var wire 32 $ a [31:0] $end
$var reg 6 % cnt [5:0] $end
$var integer 32 & i [31:0] $end
$upscope $end
$upscope $end
$enddefinitions $end
#0
$dumpvars
bx &
bx %
bx $
bx #
bx "
bx !
$end
#1000
b100000 &
b100000 %
b100000 !
b100000 #
b11111111111111111111111111111111 "
b11111111111111111111111111111111 $
#2000
b100000 &
b1111 %
b1111 !
b1111 #
b11010001100010101011011000100110 "
b11010001100010101011011000100110 $
#3000
b100000 &
b10000 %
b10000 !
b10000 #
b10110001100011111000011010101010 "
b10110001100011111000011010101010 $
#4000
b100000 &
b1110 %
b1110 !
b1110 #
b11001010000111001010001001110001 "
b11001010000111001010001001110001 $
#5000
b100000 &
b10001 %
b10001 !
b10001 #
b10100110001111000101010101111100 "
b10100110001111000101010101111100 $
#6000
b100000 &
b10001 %
b10001 !
b10001 #
b10101011101010001001010101010111 "
b10101011101010001001010101010111 $
#7000
b100000 &
b10100 %
b10100 !
b10100 #
b11010101111010101001011011101110 "
b11010101111010101001011011101110 $
#8000
b100000 &
b10100 %
b10100 !
b10100 #
b10111101001100111110111110101000 "
b10111101001100111110111110101000 $
#9000
b100000 &
b10011 %
b10011 !
b10011 #
b11111011110110001010001001110101 "
b11111011110110001010001001110101 $
#10000
b100000 &
b10100 %
b10100 !
b10100 #
b10110011101011101011101001110101 "
b10110011101011101011101001110101 $
