week2/sel2to1.v
module sel2to1(a,b,sel,out); // 2to1 selector
// 入力ポートの宣言
input a,b,sel;
// 出力ポートの宣言
output out;
// 以下より assign 文による 2to1 セレクタの出力の記述
assign out=(sel==0)?a&b:a~|b;
endmodule

week2/sel2to1_tb.v
`timescale 1 ps / 1 ps
module sel2to1_tb;
// 2to1 セレクタへの入力
reg a,b,sel;
// 2to1 セレクタからの出力
wire out;
parameter STEP = 1000;
// 2to1 セレクタを呼び出す
sel2to1 sel2to1_test(.a(a), .b(b), .sel(sel), .out(out));
initial begin
$dumpfile("sel2to1_tb.vcd");
$dumpvars(0, sel2to1_tb);
$monitor( $stime, " a=%b b=%b sel=%b out=%b", a, b, sel, out);
// STEP 毎に入力パターンを変化させて全入力パターンを網羅
#STEP a = 0; b = 0; sel = 0;
#STEP a = 0; b = 0; sel = 1;
// 以下より残りの入力パターンを与える
#STEP a = 0; b = 1; sel = 0;
#STEP a = 0; b = 1; sel = 1;
#STEP a = 1; b = 0; sel = 0;
#STEP a = 1; b = 0; sel = 1;
#STEP a = 1; b = 1; sel = 0;
#STEP a = 1; b = 1; sel = 1;
#STEP $finish; // テストベンチの終了
end
endmodule

week2/sel2to1_tb.vcd
$date
	Mon Jun 28 15:12:29 2021
$end
$version
	Icarus Verilog
$end
$timescale
	1ps
$end
$scope module sel2to1_tb $end
$var wire 1 ! out $end
$var reg 1 " a $end
$var reg 1 # b $end
$var reg 1 $ sel $end
$scope module sel2to1_test $end
$var wire 1 % a $end
$var wire 1 & b $end
$var wire 1 ! out $end
$var wire 1 ' sel $end
$upscope $end
$upscope $end
$enddefinitions $end
#0
$dumpvars
x'
x&
x%
x$
x#
x"
x!
$end
#1000
0!
0$
0'
0#
0&
0"
0%
#2000
1!
1$
1'
#3000
0!
0$
0'
1#
1&
#4000
1$
1'
#5000
0$
0'
0#
0&
1"
1%
#6000
1$
1'
#7000
1!
0$
0'
1#
1&
#8000
0!
1$
1'
