week4/counter.v
module counter ( CLK, RESETL, Q ); // 4bit counter
input   CLK, RESETL;
output  [3:0] Q;
reg [3:0] Q;
// 以下より always 文によるリセット及びカウントアップ記述
always @( posedge CLK or  negedge RESETL ) begin
    if ( RESETL == 1'b0 )
        Q=4'b0000;
    else
        Q=Q+4'b0001;
end
endmodule

week4/counter_trans.v
module counter_trans ( CLK, RESETL, OUT ); // 4bit counter
input CLK, RESETL;
output OUT;
wire [3:0] tmp; // counter の出力に接続
// counter モジュールを呼び出す
counter counter (.CLK(CLK), .RESETL(RESETL), .Q(tmp));
// 奇数個のビットが 1 の時には 1, 偶数個のビットが 1 のときには 0 を出力
assign OUT = ((tmp[3]+tmp[2]+tmp[1]+tmp[0])%2);
endmodule

week4/counter_trans_tb.v
`timescale 1ps / 1ps
module counter_trans_tb;
reg CLK, RESETL;
wire OUT;
parameter STEP = 1000;
// counter_trans を呼び出す
counter_trans counter_trans ( .CLK(CLK), .RESETL(RESETL), .OUT(OUT) );
// クロック生成
always begin
    CLK = ~CLK; #(STEP/2); // 半ステップ毎に CLK を反転してクロック生成
end
// テスト入力
initial begin
    $dumpfile("counter_trans_tb.vcd");
    $dumpvars(0, counter_trans_tb);
    $monitor( $stime, " CLK=%b RESETL=%b Q=%b OUT=%b", CLK, 
    RESETL, counter_trans.counter.Q, OUT);
    CLK = 0; RESETL = 1;
    #STEP RESETL = 0;
    #STEP RESETL = 1;
    // 20 回カウントアップして終了(20 クロック分進める)
    #(STEP*20) $finish;
end
endmodule

week4/counter_trans_tb.vcd
$date
	Mon Jul 12 15:57:32 2021
$end
$version
	Icarus Verilog
$end
$timescale
	1ps
$end
$scope module counter_trans_tb $end
$var wire 1 ! OUT $end
$var reg 1 " CLK $end
$var reg 1 # RESETL $end
$scope module counter_trans $end
$var wire 1 $ CLK $end
$var wire 1 ! OUT $end
$var wire 1 % RESETL $end
$var wire 4 & tmp [3:0] $end
$scope module counter $end
$var wire 1 $ CLK $end
$var wire 1 % RESETL $end
$var reg 4 ' Q [3:0] $end
$upscope $end
$upscope $end
$upscope $end
$enddefinitions $end
#0
$dumpvars
bx '
bx &
1%
0$
1#
0"
x!
$end
#500
1"
1$
#1000
0!
b0 '
b0 &
0"
0$
0#
0%
#1500
1"
1$
#2000
0"
0$
1#
1%
#2500
1!
b1 '
b1 &
1"
1$
#3000
0"
0$
#3500
b10 '
b10 &
1"
1$
#4000
0"
0$
#4500
0!
b11 '
b11 &
1"
1$
#5000
0"
0$
#5500
1!
b100 '
b100 &
1"
1$
#6000
0"
0$
#6500
0!
b101 '
b101 &
1"
1$
#7000
0"
0$
#7500
b110 '
b110 &
1"
1$
#8000
0"
0$
#8500
1!
b111 '
b111 &
1"
1$
#9000
0"
0$
#9500
b1000 '
b1000 &
1"
1$
#10000
0"
0$
#10500
0!
b1001 '
b1001 &
1"
1$
#11000
0"
0$
#11500
b1010 '
b1010 &
1"
1$
#12000
0"
0$
#12500
1!
b1011 '
b1011 &
1"
1$
#13000
0"
0$
#13500
0!
b1100 '
b1100 &
1"
1$
#14000
0"
0$
#14500
1!
b1101 '
b1101 &
1"
1$
#15000
0"
0$
#15500
b1110 '
b1110 &
1"
1$
#16000
0"
0$
#16500
0!
b1111 '
b1111 &
1"
1$
#17000
0"
0$
#17500
b0 '
b0 &
1"
1$
#18000
0"
0$
#18500
1!
b1 '
b1 &
1"
1$
#19000
0"
0$
#19500
b10 '
b10 &
1"
1$
#20000
0"
0$
#20500
0!
b11 '
b11 &
1"
1$
#21000
0"
0$
#21500
1!
b100 '
b100 &
1"
1$
