week3/state.v
module state ( CLK, RESETL, SW1, SW2, SW3, 
sec_resetl, min_inc, hour_inc, sec_onoff, min_onoff, 
hour_onoff );
input CLK, RESETL, SW1, SW2, SW3;
output sec_resetl, min_inc, hour_inc; 
// 秒リセット(負論理), +1 分, +1 時のカウント部への制御信号
output sec_onoff, min_onoff, hour_onoff; 
// 秒・分・時点滅の表示部への制御信号
reg [1:0] cur; // ステートレジスタ
reg [1:0] nxt; // ステート生成回路(組み合わせ回路)
// ステート名の定義
parameter NORMAL = 2'b00, SEC = 2'b01, MIN = 2'b10, HOUR = 2'b11;
// ステートレジスタ
always @( posedge CLK or negedge RESETL ) begin
    if ( !RESETL )
    cur <= NORMAL;
    else
    cur <= nxt;
end
// ステート生成回路 (組み合わせ回路)
always @( cur or SW1 or SW2 or SW3 ) begin
    case ( cur )
        NORMAL: if ( SW2 )
        nxt <= SEC; // 通常時に SW2 が押されたとき
        else
        nxt <= NORMAL; // それ以外の場合
        SEC: if ( SW2 )
        nxt <= NORMAL; // 秒修正時に SW2 が押されたとき
        else if ( SW3 )
        nxt <= HOUR; // 秒修正時に SW3 が押されたとき
        else
        nxt <= SEC; // それ以外の場合
        // 以下 NORMAL, SEC 時と同様に状態遷移図を参照して記述
        HOUR: if ( SW2 ) 
        nxt <=NORMAL;
        else if ( SW3 )
        nxt <=MIN;
        else
        nxt <=HOUR;
        MIN: if ( SW2 )
        nxt <=NORMAL;
        else if ( SW3 )
        nxt <=SEC;
        else
        nxt <=MIN;
        default:nxt <= 2'bxx; // cur が不定値になってしまったとき
    endcase
end
// 制御信号の生成
// 秒修正時に SW1 が押されたとき
assign sec_resetl = ~((cur==SEC) & SW1);
// 分修正時に SW1 が押されたとき
assign min_inc = ((cur==MIN) & SW1);
// 時修正時に SW1 が押されたとき
assign hour_inc =((cur==HOUR) & SW1);
// 秒修正時は秒点滅状態
assign sec_onoff = (cur==SEC);
// 分修正時は分点滅状態
assign min_onoff = (cur==MIN);
// 時修正時は時点滅状態
assign hour_onoff =(cur==HOUR);
endmodule

week3/state_tb.v
`timescale 1ps / 1ps
module state_tb;
reg CLK, RESETL, SW1, SW2, SW3;
wire sec_resetl, min_inc, hour_inc;
wire sec_onoff, min_onoff, hour_onoff;
integer mcd;
parameter STEP = 1000;
// ステートマシンを呼び出す
state state( CLK, RESETL, SW1, SW2, SW3, sec_resetl, min_inc, 
hour_inc, sec_onoff, min_onoff, hour_onoff );
// クロックは遷移とそれに伴う制御信号の変化に必要
always begin
    CLK = ~CLK; #(STEP/2);
end
// テスト入力
initial begin
    $dumpfile("state_tb.vcd");
    $dumpvars(0, state_tb);
    $monitor( $stime, " CLK=%b : cur=%b RESETL=%b SW1=%b SW2=%b  SW3=%b sec_resetl=%b, min_inc=%b, hour_inc=%b, sec_onoff=%b, min_onoff=%b, hour_onoff=%b", CLK, state.cur, RESETL, SW1, SW2, SW3, sec_resetl, min_inc, hour_inc, sec_onoff,min_onoff, hour_onoff);
    CLK = 0; RESETL = 1; SW1 = 0; SW2 = 0; SW3 = 0;
    #STEP RESETL = 0;
    #STEP RESETL = 1;
    // 通常時の遷移と制御信号のテスト
    // 2 つ以上の SW が同時に 1 になることを想定しない
    #STEP SW1 = 1;
    #STEP SW1 = 0; SW2 = 1;
    #(STEP*2) SW2 = 0; SW3 = 1;
    #STEP SW3 = 0; SW2 = 1;
    // 秒修正時の遷移と制御信号のテスト
    #STEP SW2 = 0; SW1 = 1;
    #STEP SW1 = 0; SW2 = 1;
    #(STEP*2) SW2 = 0; SW3 = 1;
    // 時修正時の遷移と制御信号のテスト
    #STEP SW3 = 0; SW1 = 1;
    #STEP SW1 = 0; SW2 = 1;
    #(STEP*2) SW2 = 0; SW3 = 1;
    // 分修正時の遷移と制御信号のテスト
    #(STEP*2) SW3 = 0; SW1 = 1;
    #STEP SW1 = 0; SW2 = 1;
    #(STEP*2) SW2 = 0; SW3 = 1;
    #(STEP*3) SW3 = 0; SW2 = 1;
    #STEP $finish;
end
endmodule

week3/state_tb.vcd
$date
	Mon Jul 12 12:24:40 2021
$end
$version
	Icarus Verilog
$end
$timescale
	1ps
$end
$scope module state_tb $end
$var wire 1 ! hour_inc $end
$var wire 1 " hour_onoff $end
$var wire 1 # min_inc $end
$var wire 1 $ min_onoff $end
$var wire 1 % sec_onoff $end
$var wire 1 & sec_resetl $end
$var reg 1 ' CLK $end
$var reg 1 ( RESETL $end
$var reg 1 ) SW1 $end
$var reg 1 * SW2 $end
$var reg 1 + SW3 $end
$scope module state $end
$var wire 1 , CLK $end
$var wire 1 - RESETL $end
$var wire 1 . SW1 $end
$var wire 1 / SW2 $end
$var wire 1 0 SW3 $end
$var wire 1 ! hour_inc $end
$var wire 1 " hour_onoff $end
$var wire 1 # min_inc $end
$var wire 1 $ min_onoff $end
$var wire 1 % sec_onoff $end
$var wire 1 & sec_resetl $end
$var reg 2 1 cur [1:0] $end
$var reg 2 2 nxt [1:0] $end
$upscope $end
$upscope $end
$enddefinitions $end
#0
$dumpvars
bx 2
bx 1
00
0/
0.
1-
0,
0+
0*
0)
1(
0'
1&
x%
x$
0#
x"
0!
$end
#500
1'
1,
#1000
b0 2
b0 1
0%
0$
0"
0'
0,
0(
0-
#1500
1'
1,
#2000
0'
0,
1(
1-
#2500
1'
1,
#3000
0'
0,
1)
1.
#3500
1'
1,
#4000
b1 2
0'
0,
1*
1/
0)
0.
#4500
b0 2
b1 1
1%
1'
1,
#5000
0'
0,
#5500
b1 2
b0 1
0%
1'
1,
#6000
b0 2
0'
0,
1+
10
0*
0/
#6500
1'
1,
#7000
b1 2
0'
0,
1*
1/
0+
00
#7500
b0 2
b1 1
1%
1'
1,
#8000
b1 2
0&
0'
0,
1)
1.
0*
0/
#8500
1'
1,
#9000
b0 2
1&
0'
0,
1*
1/
0)
0.
#9500
b1 2
b0 1
0%
1'
1,
#10000
0'
0,
#10500
b0 2
b1 1
1%
1'
1,
#11000
b11 2
0'
0,
1+
10
0*
0/
#11500
b10 2
b11 1
0%
1"
1'
1,
#12000
b11 2
1!
0'
0,
1)
1.
0+
00
#12500
1'
1,
#13000
b0 2
0!
0'
0,
1*
1/
0)
0.
#13500
b1 2
b0 1
0"
1'
1,
#14000
0'
0,
#14500
b0 2
b1 1
1%
1'
1,
#15000
b11 2
0'
0,
1+
10
0*
0/
#15500
b10 2
b11 1
0%
1"
1'
1,
#16000
0'
0,
#16500
b1 2
b10 1
1$
0"
1'
1,
#17000
b10 2
1#
0'
0,
1)
1.
0+
00
#17500
1'
1,
#18000
b0 2
0#
0'
0,
1*
1/
0)
0.
#18500
b1 2
b0 1
0$
1'
1,
#19000
0'
0,
#19500
b0 2
b1 1
1%
1'
1,
#20000
b11 2
0'
0,
1+
10
0*
0/
#20500
b10 2
b11 1
0%
1"
1'
1,
#21000
0'
0,
#21500
b1 2
b10 1
1$
0"
1'
1,
#22000
0'
0,
#22500
b11 2
b1 1
1%
0$
1'
1,
#23000
b0 2
0'
0,
1*
1/
0+
00
#23500
b1 2
b0 1
0%
1'
1,
